<?xml version="1.0"?>
<?mso-application progid="Excel.Sheet"?>
<Workbook xmlns="urn:schemas-microsoft-com:office:spreadsheet"
 xmlns:o="urn:schemas-microsoft-com:office:office"
 xmlns:x="urn:schemas-microsoft-com:office:excel"
 xmlns:ss="urn:schemas-microsoft-com:office:spreadsheet"
 xmlns:html="http://www.w3.org/TR/REC-html40">
 <DocumentProperties xmlns="urn:schemas-microsoft-com:office:office">
  <Author>stp01</Author>
  <LastAuthor>stp01</LastAuthor>
  <Created>1996-10-14T23:33:28Z</Created>
  <LastSaved>2011-08-03T04:32:37Z</LastSaved>
  <Version>12.00</Version>
 </DocumentProperties>
 <ExcelWorkbook xmlns="urn:schemas-microsoft-com:office:excel">
  <WindowHeight>9300</WindowHeight>
  <WindowWidth>15135</WindowWidth>
  <WindowTopX>120</WindowTopX>
  <WindowTopY>120</WindowTopY>
  <ProtectStructure>False</ProtectStructure>
  <ProtectWindows>False</ProtectWindows>
 </ExcelWorkbook>
 <Styles>
  <Style ss:ID="Default" ss:Name="Normal">
   <Alignment ss:Vertical="Bottom"/>
   <Borders/>
   <Font ss:FontName="Arial"/>
   <Interior/>
   <NumberFormat/>
   <Protection/>
  </Style>
  <Style ss:ID="m35104736">
   <Alignment ss:Horizontal="Left" ss:Vertical="Bottom"/>
   <Borders>
    <Border ss:Position="Right" ss:LineStyle="Continuous" ss:Weight="2"/>
   </Borders>
  </Style>
  <Style ss:ID="m35104756">
   <Alignment ss:Horizontal="Left" ss:Vertical="Bottom"/>
   <Borders>
    <Border ss:Position="Right" ss:LineStyle="Continuous" ss:Weight="2"/>
   </Borders>
  </Style>
  <Style ss:ID="m35104512">
   <Alignment ss:Horizontal="Left" ss:Vertical="Bottom"/>
   <Borders>
    <Border ss:Position="Right" ss:LineStyle="Continuous" ss:Weight="2"/>
   </Borders>
  </Style>
  <Style ss:ID="m35104532">
   <Alignment ss:Horizontal="Left" ss:Vertical="Bottom"/>
   <Borders>
    <Border ss:Position="Right" ss:LineStyle="Continuous" ss:Weight="2"/>
   </Borders>
  </Style>
  <Style ss:ID="m35104552">
   <Alignment ss:Horizontal="Left" ss:Vertical="Bottom"/>
   <Borders>
    <Border ss:Position="Right" ss:LineStyle="Continuous" ss:Weight="2"/>
   </Borders>
  </Style>
  <Style ss:ID="m35104572">
   <Alignment ss:Horizontal="Left" ss:Vertical="Bottom"/>
   <Borders>
    <Border ss:Position="Right" ss:LineStyle="Continuous" ss:Weight="2"/>
   </Borders>
  </Style>
  <Style ss:ID="m35104592">
   <Alignment ss:Horizontal="Left" ss:Vertical="Bottom"/>
   <Borders>
    <Border ss:Position="Right" ss:LineStyle="Continuous" ss:Weight="2"/>
   </Borders>
  </Style>
  <Style ss:ID="m35104612">
   <Alignment ss:Horizontal="Left" ss:Vertical="Bottom"/>
   <Borders>
    <Border ss:Position="Right" ss:LineStyle="Continuous" ss:Weight="2"/>
   </Borders>
  </Style>
  <Style ss:ID="m35104632">
   <Alignment ss:Horizontal="Left" ss:Vertical="Bottom"/>
   <Borders>
    <Border ss:Position="Right" ss:LineStyle="Continuous" ss:Weight="2"/>
   </Borders>
  </Style>
  <Style ss:ID="m35104652">
   <Alignment ss:Horizontal="Left" ss:Vertical="Bottom"/>
   <Borders>
    <Border ss:Position="Right" ss:LineStyle="Continuous" ss:Weight="2"/>
   </Borders>
  </Style>
  <Style ss:ID="m35104672">
   <Alignment ss:Horizontal="Left" ss:Vertical="Bottom"/>
   <Borders>
    <Border ss:Position="Right" ss:LineStyle="Continuous" ss:Weight="2"/>
   </Borders>
  </Style>
  <Style ss:ID="m35104692">
   <Alignment ss:Horizontal="Left" ss:Vertical="Bottom"/>
   <Borders>
    <Border ss:Position="Right" ss:LineStyle="Continuous" ss:Weight="2"/>
   </Borders>
  </Style>
  <Style ss:ID="m35104288">
   <Alignment ss:Horizontal="Left" ss:Vertical="Bottom"/>
   <Borders>
    <Border ss:Position="Bottom" ss:LineStyle="Continuous" ss:Weight="2"/>
    <Border ss:Position="Right" ss:LineStyle="Continuous" ss:Weight="2"/>
   </Borders>
  </Style>
  <Style ss:ID="m35104308">
   <Alignment ss:Horizontal="Left" ss:Vertical="Bottom"/>
   <Borders>
    <Border ss:Position="Right" ss:LineStyle="Continuous" ss:Weight="2"/>
   </Borders>
  </Style>
  <Style ss:ID="m35104328">
   <Alignment ss:Horizontal="Left" ss:Vertical="Bottom"/>
   <Borders>
    <Border ss:Position="Right" ss:LineStyle="Continuous" ss:Weight="2"/>
   </Borders>
  </Style>
  <Style ss:ID="m35104348">
   <Alignment ss:Horizontal="Left" ss:Vertical="Bottom"/>
   <Borders>
    <Border ss:Position="Right" ss:LineStyle="Continuous" ss:Weight="2"/>
   </Borders>
  </Style>
  <Style ss:ID="m35104368">
   <Alignment ss:Horizontal="Left" ss:Vertical="Bottom"/>
   <Borders>
    <Border ss:Position="Right" ss:LineStyle="Continuous" ss:Weight="2"/>
   </Borders>
  </Style>
  <Style ss:ID="m35104388">
   <Alignment ss:Horizontal="Left" ss:Vertical="Bottom"/>
   <Borders>
    <Border ss:Position="Right" ss:LineStyle="Continuous" ss:Weight="2"/>
   </Borders>
  </Style>
  <Style ss:ID="m35104408">
   <Alignment ss:Horizontal="Left" ss:Vertical="Bottom"/>
   <Borders>
    <Border ss:Position="Right" ss:LineStyle="Continuous" ss:Weight="2"/>
   </Borders>
  </Style>
  <Style ss:ID="m35104428">
   <Alignment ss:Horizontal="Left" ss:Vertical="Bottom"/>
   <Borders>
    <Border ss:Position="Right" ss:LineStyle="Continuous" ss:Weight="2"/>
   </Borders>
  </Style>
  <Style ss:ID="m35104448">
   <Alignment ss:Horizontal="Left" ss:Vertical="Bottom" ss:WrapText="1"/>
   <Borders>
    <Border ss:Position="Right" ss:LineStyle="Continuous" ss:Weight="2"/>
   </Borders>
  </Style>
  <Style ss:ID="m35104468">
   <Alignment ss:Horizontal="Left" ss:Vertical="Bottom"/>
   <Borders>
    <Border ss:Position="Right" ss:LineStyle="Continuous" ss:Weight="2"/>
   </Borders>
  </Style>
  <Style ss:ID="m35104064">
   <Alignment ss:Horizontal="Center" ss:Vertical="Center"/>
   <Borders>
    <Border ss:Position="Left" ss:LineStyle="Continuous" ss:Weight="2"/>
    <Border ss:Position="Right" ss:LineStyle="Continuous" ss:Weight="2"/>
    <Border ss:Position="Top" ss:LineStyle="Continuous" ss:Weight="2"/>
   </Borders>
   <Font ss:FontName="Arial" x:Family="Swiss" ss:Bold="1"/>
  </Style>
  <Style ss:ID="m35104084">
   <Alignment ss:Horizontal="Left" ss:Vertical="Center"/>
   <Borders>
    <Border ss:Position="Left" ss:LineStyle="Continuous" ss:Weight="2"/>
    <Border ss:Position="Right" ss:LineStyle="Continuous" ss:Weight="2"/>
   </Borders>
   <Font ss:FontName="Arial" x:Family="Swiss" ss:Bold="1"/>
  </Style>
  <Style ss:ID="m35104104">
   <Alignment ss:Horizontal="Left" ss:Vertical="Center"/>
   <Borders>
    <Border ss:Position="Left" ss:LineStyle="Continuous" ss:Weight="2"/>
    <Border ss:Position="Right" ss:LineStyle="Continuous" ss:Weight="2"/>
   </Borders>
   <Font ss:FontName="Arial" x:Family="Swiss" ss:Bold="1"/>
  </Style>
  <Style ss:ID="m35104124">
   <Alignment ss:Horizontal="Left" ss:Vertical="Bottom"/>
   <Borders>
    <Border ss:Position="Right" ss:LineStyle="Continuous" ss:Weight="2"/>
   </Borders>
  </Style>
  <Style ss:ID="m35104144">
   <Alignment ss:Horizontal="Left" ss:Vertical="Bottom"/>
   <Borders>
    <Border ss:Position="Right" ss:LineStyle="Continuous" ss:Weight="2"/>
   </Borders>
  </Style>
  <Style ss:ID="m35104164">
   <Alignment ss:Horizontal="Left" ss:Vertical="Bottom"/>
   <Borders>
    <Border ss:Position="Right" ss:LineStyle="Continuous" ss:Weight="2"/>
   </Borders>
  </Style>
  <Style ss:ID="m35104184">
   <Alignment ss:Horizontal="Left" ss:Vertical="Bottom"/>
   <Borders>
    <Border ss:Position="Right" ss:LineStyle="Continuous" ss:Weight="2"/>
   </Borders>
  </Style>
  <Style ss:ID="m35104204">
   <Alignment ss:Horizontal="Left" ss:Vertical="Bottom"/>
   <Borders>
    <Border ss:Position="Right" ss:LineStyle="Continuous" ss:Weight="2"/>
   </Borders>
  </Style>
  <Style ss:ID="m35104224">
   <Alignment ss:Horizontal="Left" ss:Vertical="Bottom"/>
   <Borders>
    <Border ss:Position="Right" ss:LineStyle="Continuous" ss:Weight="2"/>
   </Borders>
  </Style>
  <Style ss:ID="m35104244">
   <Alignment ss:Horizontal="Left" ss:Vertical="Bottom"/>
   <Borders>
    <Border ss:Position="Right" ss:LineStyle="Continuous" ss:Weight="2"/>
   </Borders>
  </Style>
  <Style ss:ID="s62">
   <Font ss:FontName="Arial" x:Family="Swiss"/>
  </Style>
  <Style ss:ID="s63">
   <Alignment ss:Horizontal="Center" ss:Vertical="Bottom"/>
   <Font ss:FontName="Arial" x:Family="Swiss" ss:Size="11" ss:Color="#0000FF"
    ss:Bold="1"/>
  </Style>
  <Style ss:ID="s64">
   <Alignment ss:Horizontal="Center" ss:Vertical="Bottom"/>
   <Font ss:FontName="Arial" x:Family="Swiss"/>
  </Style>
  <Style ss:ID="s65">
   <Alignment ss:Horizontal="Left" ss:Vertical="Bottom" ss:Indent="4"/>
   <Font ss:FontName="Arial" x:Family="Swiss"/>
  </Style>
  <Style ss:ID="s66">
   <Alignment ss:Horizontal="Left" ss:Vertical="Bottom" ss:Indent="15"/>
   <Font ss:FontName="Arial" x:Family="Swiss"/>
  </Style>
  <Style ss:ID="s67">
   <Alignment ss:Horizontal="Justify" ss:Vertical="Bottom"/>
   <Font ss:FontName="Arial" x:Family="Swiss"/>
  </Style>
  <Style ss:ID="s68">
   <Font ss:FontName="Arial" x:Family="Swiss"/>
   <NumberFormat ss:Format="@"/>
  </Style>
  <Style ss:ID="s69">
   <Alignment ss:Horizontal="Center" ss:Vertical="Center" ss:WrapText="1"/>
   <Borders>
    <Border ss:Position="Bottom" ss:LineStyle="Continuous" ss:Weight="1"/>
    <Border ss:Position="Left" ss:LineStyle="Continuous" ss:Weight="1"/>
    <Border ss:Position="Right" ss:LineStyle="Continuous" ss:Weight="1"/>
    <Border ss:Position="Top" ss:LineStyle="Continuous" ss:Weight="1"/>
   </Borders>
   <Font ss:FontName="Arial" x:Family="Swiss" ss:Size="9" ss:Bold="1"/>
   <NumberFormat ss:Format="@"/>
  </Style>
  <Style ss:ID="s70">
   <Alignment ss:Horizontal="Center" ss:Vertical="Bottom" ss:WrapText="1"/>
   <Borders>
    <Border ss:Position="Bottom" ss:LineStyle="Continuous" ss:Weight="1"/>
    <Border ss:Position="Left" ss:LineStyle="Continuous" ss:Weight="1"/>
    <Border ss:Position="Right" ss:LineStyle="Continuous" ss:Weight="1"/>
    <Border ss:Position="Top" ss:LineStyle="Continuous" ss:Weight="1"/>
   </Borders>
   <Font ss:FontName="Arial" x:Family="Swiss"/>
  </Style>
  <Style ss:ID="s71">
   <Alignment ss:Horizontal="Center" ss:Vertical="Bottom" ss:WrapText="1"/>
   <Borders>
    <Border ss:Position="Bottom" ss:LineStyle="Continuous" ss:Weight="1"/>
    <Border ss:Position="Left" ss:LineStyle="Continuous" ss:Weight="1"/>
    <Border ss:Position="Right" ss:LineStyle="Continuous" ss:Weight="1"/>
    <Border ss:Position="Top" ss:LineStyle="Continuous" ss:Weight="1"/>
   </Borders>
   <Font ss:FontName="Arial" x:Family="Swiss"/>
   <NumberFormat ss:Format="@"/>
  </Style>
  <Style ss:ID="s72">
   <Alignment ss:Horizontal="Center" ss:Vertical="Top" ss:WrapText="1"/>
   <Borders>
    <Border ss:Position="Bottom" ss:LineStyle="Continuous" ss:Weight="1"/>
    <Border ss:Position="Left" ss:LineStyle="Continuous" ss:Weight="1"/>
    <Border ss:Position="Right" ss:LineStyle="Continuous" ss:Weight="1"/>
    <Border ss:Position="Top" ss:LineStyle="Continuous" ss:Weight="1"/>
   </Borders>
   <Font ss:FontName="Arial" x:Family="Swiss"/>
   <NumberFormat ss:Format="@"/>
  </Style>
  <Style ss:ID="s73">
   <Alignment ss:Vertical="Top" ss:WrapText="1"/>
   <Borders>
    <Border ss:Position="Bottom" ss:LineStyle="Continuous" ss:Weight="1"/>
    <Border ss:Position="Left" ss:LineStyle="Continuous" ss:Weight="1"/>
    <Border ss:Position="Right" ss:LineStyle="Continuous" ss:Weight="1"/>
    <Border ss:Position="Top" ss:LineStyle="Continuous" ss:Weight="1"/>
   </Borders>
   <Font ss:FontName="Arial" x:Family="Swiss"/>
   <NumberFormat ss:Format="@"/>
  </Style>
  <Style ss:ID="s74">
   <Alignment ss:Horizontal="Center" ss:Vertical="Center" ss:WrapText="1"/>
   <Borders>
    <Border ss:Position="Bottom" ss:LineStyle="Continuous" ss:Weight="1"/>
    <Border ss:Position="Left" ss:LineStyle="Continuous" ss:Weight="1"/>
    <Border ss:Position="Right" ss:LineStyle="Continuous" ss:Weight="1"/>
    <Border ss:Position="Top" ss:LineStyle="Continuous" ss:Weight="1"/>
   </Borders>
   <Font ss:FontName="Arial" x:Family="Swiss"/>
   <NumberFormat ss:Format="@"/>
  </Style>
  <Style ss:ID="s75">
   <Alignment ss:Vertical="Top" ss:WrapText="1"/>
   <Borders>
    <Border ss:Position="Bottom" ss:LineStyle="Continuous" ss:Weight="1"/>
    <Border ss:Position="Left" ss:LineStyle="Continuous" ss:Weight="1"/>
    <Border ss:Position="Right" ss:LineStyle="Continuous" ss:Weight="1"/>
    <Border ss:Position="Top" ss:LineStyle="Continuous" ss:Weight="1"/>
   </Borders>
   <Font ss:FontName="Arial" x:Family="Swiss"/>
   <NumberFormat ss:Format="#,##0"/>
  </Style>
  <Style ss:ID="s76">
   <Font ss:FontName="Arial" x:Family="Swiss"/>
   <NumberFormat ss:Format="0"/>
  </Style>
  <Style ss:ID="s77">
   <Alignment ss:Horizontal="Center" ss:Vertical="Bottom" ss:WrapText="1"/>
   <Borders>
    <Border ss:Position="Bottom" ss:LineStyle="Continuous" ss:Weight="1"/>
    <Border ss:Position="Left" ss:LineStyle="Continuous" ss:Weight="1"/>
    <Border ss:Position="Right" ss:LineStyle="Continuous" ss:Weight="1"/>
    <Border ss:Position="Top" ss:LineStyle="Continuous" ss:Weight="1"/>
   </Borders>
   <Font ss:FontName="Arial" x:Family="Swiss"/>
   <NumberFormat ss:Format="0"/>
  </Style>
  <Style ss:ID="s78">
   <Alignment ss:Vertical="Top" ss:WrapText="1"/>
   <Borders>
    <Border ss:Position="Bottom" ss:LineStyle="Continuous" ss:Weight="1"/>
    <Border ss:Position="Right" ss:LineStyle="Continuous" ss:Weight="1"/>
    <Border ss:Position="Top" ss:LineStyle="Continuous" ss:Weight="1"/>
   </Borders>
   <Font ss:FontName="Arial" x:Family="Swiss"/>
  </Style>
  <Style ss:ID="s79">
   <Alignment ss:Vertical="Top" ss:WrapText="1"/>
   <Borders>
    <Border ss:Position="Bottom" ss:LineStyle="Continuous" ss:Weight="1"/>
    <Border ss:Position="Top" ss:LineStyle="Continuous" ss:Weight="1"/>
   </Borders>
   <Font ss:FontName="Arial" x:Family="Swiss"/>
   <NumberFormat ss:Format="#,##0"/>
  </Style>
  <Style ss:ID="s80">
   <Alignment ss:Vertical="Top" ss:WrapText="1"/>
   <Borders>
    <Border ss:Position="Bottom" ss:LineStyle="Continuous" ss:Weight="1"/>
    <Border ss:Position="Top" ss:LineStyle="Continuous" ss:Weight="1"/>
   </Borders>
   <Font ss:FontName="Arial" x:Family="Swiss"/>
   <NumberFormat ss:Format="@"/>
  </Style>
  <Style ss:ID="s81">
   <Borders>
    <Border ss:Position="Left" ss:LineStyle="Continuous" ss:Weight="2"/>
   </Borders>
  </Style>
  <Style ss:ID="s82">
   <Borders/>
  </Style>
  <Style ss:ID="s83">
   <Borders>
    <Border ss:Position="Right" ss:LineStyle="Continuous" ss:Weight="2"/>
   </Borders>
  </Style>
  <Style ss:ID="s84">
   <Borders>
    <Border ss:Position="Bottom" ss:LineStyle="Continuous" ss:Weight="2"/>
    <Border ss:Position="Left" ss:LineStyle="Continuous" ss:Weight="2"/>
   </Borders>
  </Style>
  <Style ss:ID="s85">
   <Borders>
    <Border ss:Position="Bottom" ss:LineStyle="Continuous" ss:Weight="2"/>
   </Borders>
  </Style>
  <Style ss:ID="s86">
   <Alignment ss:Vertical="Top" ss:WrapText="1"/>
   <Borders>
    <Border ss:Position="Bottom" ss:LineStyle="Continuous" ss:Weight="1"/>
    <Border ss:Position="Left" ss:LineStyle="Continuous" ss:Weight="1"/>
    <Border ss:Position="Right" ss:LineStyle="Continuous" ss:Weight="1"/>
    <Border ss:Position="Top" ss:LineStyle="Continuous" ss:Weight="1"/>
   </Borders>
   <Font ss:FontName="Arial" x:Family="Swiss" ss:Bold="1"/>
  </Style>
  <Style ss:ID="s87">
   <Alignment ss:Vertical="Top" ss:WrapText="1"/>
   <Borders>
    <Border ss:Position="Bottom" ss:LineStyle="Continuous" ss:Weight="1"/>
    <Border ss:Position="Left" ss:LineStyle="Continuous" ss:Weight="1"/>
    <Border ss:Position="Right" ss:LineStyle="Continuous" ss:Weight="1"/>
    <Border ss:Position="Top" ss:LineStyle="Continuous" ss:Weight="1"/>
   </Borders>
   <Font ss:FontName="Arial" x:Family="Swiss" ss:Bold="1"/>
   <NumberFormat ss:Format="@"/>
  </Style>
  <Style ss:ID="s88">
   <Alignment ss:Vertical="Top" ss:WrapText="1"/>
   <Borders>
    <Border ss:Position="Bottom" ss:LineStyle="Continuous" ss:Weight="1"/>
    <Border ss:Position="Left" ss:LineStyle="Continuous" ss:Weight="1"/>
    <Border ss:Position="Right" ss:LineStyle="Continuous" ss:Weight="1"/>
    <Border ss:Position="Top" ss:LineStyle="Continuous" ss:Weight="1"/>
   </Borders>
   <Font ss:FontName="Arial" x:Family="Swiss" ss:Bold="1"/>
   <NumberFormat ss:Format="#,##0"/>
  </Style>
  <Style ss:ID="s89">
   <Font ss:FontName="Arial" x:Family="Swiss" ss:Bold="1"/>
  </Style>
  <Style ss:ID="s90">
   <Alignment ss:Vertical="Top" ss:WrapText="1"/>
   <Borders>
    <Border ss:Position="Bottom" ss:LineStyle="Continuous" ss:Weight="1"/>
    <Border ss:Position="Left" ss:LineStyle="Continuous" ss:Weight="1"/>
    <Border ss:Position="Right" ss:LineStyle="Continuous" ss:Weight="1"/>
    <Border ss:Position="Top" ss:LineStyle="Continuous" ss:Weight="1"/>
   </Borders>
   <Font ss:FontName="Arial" x:Family="Swiss"/>
   <NumberFormat ss:Format="dd/mm/yyyy;@"/>
  </Style>
  <Style ss:ID="s91">
   <Alignment ss:Horizontal="Left" ss:Vertical="Bottom"/>
   <Borders/>
  </Style>
  <Style ss:ID="s112">
   <Alignment ss:Horizontal="Center" ss:Vertical="Center" ss:WrapText="1"/>
   <Borders>
    <Border ss:Position="Bottom" ss:LineStyle="Continuous" ss:Weight="1"/>
    <Border ss:Position="Left" ss:LineStyle="Continuous" ss:Weight="1"/>
    <Border ss:Position="Right" ss:LineStyle="Continuous" ss:Weight="1"/>
    <Border ss:Position="Top" ss:LineStyle="Continuous" ss:Weight="1"/>
   </Borders>
   <Font ss:FontName="Arial" x:Family="Swiss" ss:Size="9" ss:Bold="1"/>
   <NumberFormat ss:Format="0"/>
  </Style>
  <Style ss:ID="s114">
   <Alignment ss:Horizontal="Left" ss:Vertical="Top" ss:WrapText="1"/>
   <Borders>
    <Border ss:Position="Bottom" ss:LineStyle="Continuous" ss:Weight="1"/>
    <Border ss:Position="Left" ss:LineStyle="Continuous" ss:Weight="1"/>
    <Border ss:Position="Top" ss:LineStyle="Continuous" ss:Weight="1"/>
   </Borders>
   <Font ss:FontName="Arial" x:Family="Swiss"/>
   <NumberFormat ss:Format="@"/>
  </Style>
  <Style ss:ID="s116">
   <Alignment ss:Horizontal="Left" ss:Vertical="Bottom"/>
   <Font ss:FontName="Arial" x:Family="Swiss"/>
  </Style>
  <Style ss:ID="s117">
   <Alignment ss:Horizontal="Right" ss:Vertical="Bottom"/>
   <Borders/>
   <Font ss:FontName="Arial" x:Family="Swiss"/>
  </Style>
 </Styles>
 <Worksheet ss:Name="Sheet1">
  <Table ss:ExpandedColumnCount="12" x:FullColumns="1"
   x:FullRows="1" ss:StyleID="s62">
   <Column ss:StyleID="s62" ss:AutoFitWidth="0" ss:Width="11.25"/>
   <Column ss:Index="3" ss:StyleID="s68" ss:AutoFitWidth="0" ss:Width="58.5"/>
   <Column ss:StyleID="s62" ss:AutoFitWidth="0" ss:Width="68.25"/>
   <Column ss:StyleID="s68" ss:AutoFitWidth="0" ss:Width="64.5"/>
   <Column ss:StyleID="s68" ss:AutoFitWidth="0" ss:Width="73.5"/>
   <Column ss:StyleID="s68" ss:AutoFitWidth="0" ss:Width="58.5"/>
   <Column ss:StyleID="s68" ss:AutoFitWidth="0" ss:Width="69.75"/>
   <Column ss:StyleID="s62" ss:AutoFitWidth="0" ss:Width="57"/>
   <Column ss:StyleID="s76" ss:AutoFitWidth="0" ss:Width="54.75"/>
   <Column ss:StyleID="s62" ss:AutoFitWidth="0" ss:Width="64.5"/>
   <Column ss:StyleID="s68" ss:AutoFitWidth="0" ss:Width="69"/>
   <Row ss:Index="3" ss:Height="15">
    <Cell ss:Index="2" ss:StyleID="s63"/>
   </Row>
   <Row ss:Height="15">
    <Cell ss:Index="2" ss:MergeAcross="10" ss:StyleID="s63"><Data ss:Type="String">BẢNG KÊ HOÁ ĐƠN, CHỨNG TỪ HÀNG HOÁ, DỊCH VỤ MUA VÀO</Data></Cell>
   </Row>
   <Row ss:Height="15" ss:Hidden="1">
    <Cell><Data ss:Type="String">Bangkemuavao.xls</Data></Cell>
    <Cell ss:MergeAcross="10" ss:StyleID="s63"/>
   </Row>
   <Row>
    <Cell ss:Index="2" ss:MergeAcross="10" ss:StyleID="s64"><Data ss:Type="String">(Kèm theo tờ khai thuế GTGT theo mẫu số 01/GTGT)</Data></Cell>
   </Row>
   <Row>
    <Cell ss:Index="2" ss:MergeAcross="10" ss:StyleID="s64"><Data ss:Type="String">Kỳ tính thuế: Tháng #ky# năm #nam# </Data></Cell>
   </Row>
   <Row>
    <Cell ss:Index="2" ss:StyleID="s64"/>
   </Row>
   <Row>
    <Cell ss:Index="2" ss:MergeAcross="10" ss:StyleID="s116"><Data ss:Type="String">Người nộp thuế: #cty_nnt#       </Data></Cell>
   </Row>
   <Row>
    <Cell ss:Index="2" ss:MergeAcross="10" ss:StyleID="s116"><Data ss:Type="String">Mã số thuế: #cty_mst#</Data></Cell>
   </Row>
   <Row>
    <Cell ss:Index="2" ss:StyleID="s65"/>
   </Row>
   <Row>
    <Cell ss:Index="2" ss:MergeAcross="10" ss:StyleID="s117"><Data ss:Type="String">Đơn vị tiền: đồng Việt Nam</Data></Cell>
   </Row>
   <Row ss:AutoFitHeight="0">
    <Cell ss:Index="2" ss:MergeDown="2" ss:StyleID="s69"><Data ss:Type="String">STT</Data><Comment
      ss:Author="FIS-CMCSOFT"><ss:Data xmlns="http://www.w3.org/TR/REC-html40"><Font
        html:Face="Tahoma" x:Family="Swiss" html:Size="8" html:Color="#000000">Thông tin này không bắt buộc phải nhập</Font></ss:Data></Comment></Cell>
    <Cell ss:MergeAcross="2" ss:MergeDown="1" ss:StyleID="s69"><Data
      ss:Type="String">Hoá đơn, chứng từ, biên lai nộp thuế</Data></Cell>
    <Cell ss:MergeDown="2" ss:StyleID="s69"><Data ss:Type="String">Tên người bán</Data></Cell>
    <Cell ss:MergeDown="2" ss:StyleID="s69"><Data ss:Type="String">Mã số thuế người bán</Data><Comment
      ss:Author="FIS-CMCSOFT"><ss:Data xmlns="http://www.w3.org/TR/REC-html40"><Font
        html:Face="Tahoma" x:Family="Swiss" html:Size="8" html:Color="#000000">Mã sô thuế theo hóa đơn mua hàng</Font></ss:Data></Comment></Cell>
    <Cell ss:MergeDown="2" ss:StyleID="s69"><Data ss:Type="String">Mặt hàng</Data><Comment
      ss:Author="FIS-CMCSOFT"><ss:Data xmlns="http://www.w3.org/TR/REC-html40"><Font
        html:Face="Tahoma" x:Family="Swiss" html:Size="8" html:Color="#000000">Tên loại mặt hàng</Font></ss:Data></Comment></Cell>
    <Cell ss:MergeDown="2" ss:StyleID="s69"><Data ss:Type="String">Doanh số mua chưa có thuế</Data></Cell>
    <Cell ss:MergeDown="2" ss:StyleID="s112"><Data ss:Type="String">Thuế suất</Data><Comment
      ss:Author="FIS-CMCSOFT"><ss:Data xmlns="http://www.w3.org/TR/REC-html40"><Font
        html:Face="Tahoma" x:Family="Swiss" html:Size="8" html:Color="#000000">Thuế suất thuế GTGT định dạng là text. Nếu thuế suất 10% nhập là 10, 5% nhập là 5</Font></ss:Data></Comment></Cell>
    <Cell ss:MergeDown="2" ss:StyleID="s69"><Data ss:Type="String">Thuế GTGT</Data></Cell>
    <Cell ss:MergeDown="2" ss:StyleID="s69"><Data ss:Type="String">Ghi chú</Data></Cell>
   </Row>
   <Row ss:AutoFitHeight="0" ss:Height="4.5"/>
   <Row ss:AutoFitHeight="0" ss:Height="35.25">
    <Cell ss:Index="3" ss:StyleID="s69"><Data ss:Type="String">Ký hiệu hoá đơn</Data><Comment
      ss:Author="FIS-CMCSOFT"><ss:Data xmlns="http://www.w3.org/TR/REC-html40"><Font
        html:Face="Tahoma" x:Family="Swiss" html:Size="8" html:Color="#000000">Nhập ký hiệu hóa đơn</Font></ss:Data></Comment></Cell>
    <Cell ss:StyleID="s69"><Data ss:Type="String">Số hoá đơn</Data><Comment
      ss:Author="FIS-CMCSOFT"><ss:Data xmlns="http://www.w3.org/TR/REC-html40"><Font
        html:Face="Tahoma" x:Family="Swiss" html:Size="8" html:Color="#000000">Nhập số hóa đơn</Font></ss:Data></Comment></Cell>
    <Cell ss:StyleID="s69"><Data ss:Type="String">Ngày, tháng, năm phát hành</Data><Comment
      ss:Author="FIS-CMCSOFT"><ss:Data xmlns="http://www.w3.org/TR/REC-html40"><Font
        html:Face="Tahoma" x:Family="Swiss" html:Size="8" html:Color="#000000">Nhập ngày tháng năm phát hành hóa đơn theo đúng định dạng sau DD/MM/YYYY</Font></ss:Data></Comment></Cell>
   </Row>
   <Row>
    <Cell ss:Index="2" ss:StyleID="s70"><Data ss:Type="String">[1]</Data></Cell>
    <Cell ss:StyleID="s71"><Data ss:Type="String">[2]</Data></Cell>
    <Cell ss:StyleID="s70"><Data ss:Type="String">[3]</Data></Cell>
    <Cell ss:StyleID="s71"><Data ss:Type="String">[4]</Data></Cell>
    <Cell ss:StyleID="s71"><Data ss:Type="String">[5]</Data></Cell>
    <Cell ss:StyleID="s72"><Data ss:Type="String">[6]</Data></Cell>
    <Cell ss:StyleID="s72"><Data ss:Type="String">[7]</Data></Cell>
    <Cell ss:StyleID="s70"><Data ss:Type="String">[8]</Data></Cell>
    <Cell ss:StyleID="s77"><Data ss:Type="String">[9]</Data></Cell>
    <Cell ss:StyleID="s70"><Data ss:Type="String">[10]</Data></Cell>
    <Cell ss:StyleID="s71"><Data ss:Type="String">[11]</Data></Cell>
   </Row>
   <Row ss:AutoFitHeight="0">
    <Cell ss:Index="2" ss:MergeAcross="6" ss:StyleID="s114"><Data ss:Type="String">1. Hàng hoá, dịch vụ dùng riêng cho SXKD chịu thuế GTGT đủ điều kiện khấu trừ thuế:</Data></Cell>
    <Cell ss:StyleID="s79"/>
    <Cell ss:StyleID="s80"/>
    <Cell ss:StyleID="s79"/>
    <Cell ss:StyleID="s78"/>
   </Row>
   <!--beginDetail-->
   <!--table:0--table-->
   <!--where:ma_tc='1' and sysorder =5--where-->
   <Row>
    <Cell ss:Index="2" ss:StyleID="s73"><Data ss:Type="String">#stt#</Data></Cell>
    <Cell ss:StyleID="s73"><Data ss:Type="String">#so_seri#</Data></Cell>
    <Cell ss:StyleID="s73"><Data ss:Type="String">#so_hd#</Data></Cell>
    <Cell ss:StyleID="s90">#ngay_hd#</Cell>
    <Cell ss:StyleID="s73"><Data ss:Type="String">#ten_kh#</Data></Cell>
    <Cell ss:StyleID="s74"><Data ss:Type="String">#ma_so_thue#</Data></Cell>
    <Cell ss:StyleID="s73"><Data ss:Type="String">#ten_vt#</Data></Cell>
    <Cell ss:StyleID="s75"><Data ss:Type="Number">#t_tien#</Data></Cell>
    <Cell ss:StyleID="s73"><Data ss:Type="String">#thue_suat#</Data></Cell>
    <Cell ss:StyleID="s75"><Data ss:Type="Number">#t_thue#</Data></Cell>
    <Cell ss:StyleID="s73"><Data ss:Type="String">#ghi_chu#</Data></Cell>
   </Row>
   <!--endDetail-->
   <!--beginDetail-->
   <!--where:ma_tc='1' and sysorder =3--where-->
   <Row ss:StyleID="s89">
    <Cell ss:Index="2" ss:StyleID="s86"><Data ss:Type="String">Tổng</Data></Cell>
    <Cell ss:StyleID="s87"/>
    <Cell ss:StyleID="s86"/>
    <Cell ss:StyleID="s87"/>
    <Cell ss:StyleID="s87"/>
    <Cell ss:StyleID="s87"/>
    <Cell ss:StyleID="s87"/>
    <Cell ss:StyleID="s88"><Data ss:Type="Number">#t_tien#</Data></Cell>
    <Cell ss:StyleID="s87"/>
    <Cell ss:StyleID="s88"><Data ss:Type="Number">#t_thue#</Data></Cell>
    <Cell ss:StyleID="s87"/>
   </Row>
   <!--endDetail-->
   <Row ss:AutoFitHeight="0">
    <Cell ss:Index="2" ss:MergeAcross="6" ss:StyleID="s114"><Data ss:Type="String">2. Hàng hoá, dịch vụ không đủ điều kiện khấu trừ:</Data></Cell>
    <Cell ss:StyleID="s79"/>
    <Cell ss:StyleID="s80"/>
    <Cell ss:StyleID="s79"/>
    <Cell ss:StyleID="s78"/>
   </Row>
   <!--beginDetail-->
   <!--where:ma_tc='2' and sysorder =5--where-->
   <Row>
    <Cell ss:Index="2" ss:StyleID="s73"><Data ss:Type="String">#stt#</Data></Cell>
    <Cell ss:StyleID="s73"><Data ss:Type="String">#so_seri#</Data></Cell>
    <Cell ss:StyleID="s73"><Data ss:Type="String">#so_hd#</Data></Cell>
    <Cell ss:StyleID="s90">#ngay_hd#</Cell>
    <Cell ss:StyleID="s73"><Data ss:Type="String">#ten_kh#</Data></Cell>
    <Cell ss:StyleID="s74"><Data ss:Type="String">#ma_so_thue#</Data></Cell>
    <Cell ss:StyleID="s73"><Data ss:Type="String">#ten_vt#</Data></Cell>
    <Cell ss:StyleID="s75"><Data ss:Type="Number">#t_tien#</Data></Cell>
    <Cell ss:StyleID="s73"><Data ss:Type="String">#thue_suat#</Data></Cell>
    <Cell ss:StyleID="s75"><Data ss:Type="Number">#t_thue#</Data></Cell>
    <Cell ss:StyleID="s73"><Data ss:Type="String">#ghi_chu#</Data></Cell>
   </Row>
   <!--endDetail-->
   <!--beginDetail-->
   <!--where:ma_tc='2' and sysorder =3--where-->
   <Row ss:StyleID="s89">
    <Cell ss:Index="2" ss:StyleID="s86"><Data ss:Type="String">Tổng</Data></Cell>
    <Cell ss:StyleID="s87"/>
    <Cell ss:StyleID="s86"/>
    <Cell ss:StyleID="s87"/>
    <Cell ss:StyleID="s87"/>
    <Cell ss:StyleID="s87"/>
    <Cell ss:StyleID="s87"/>
    <Cell ss:StyleID="s88"><Data ss:Type="Number">#t_tien#</Data></Cell>
    <Cell ss:StyleID="s87"/>
    <Cell ss:StyleID="s88"><Data ss:Type="Number">#t_thue#</Data></Cell>
    <Cell ss:StyleID="s87"/>
   </Row>
   <!--endDetail-->
   <Row ss:AutoFitHeight="0">
    <Cell ss:Index="2" ss:MergeAcross="6" ss:StyleID="s114"><Data ss:Type="String">3. Hàng hoá, dịch vụ dùng chung cho SXKD chịu thuế và không chịu thuế đủ điều kiện khấu trừ thuế:</Data></Cell>
    <Cell ss:StyleID="s79"/>
    <Cell ss:StyleID="s80"/>
    <Cell ss:StyleID="s79"/>
    <Cell ss:StyleID="s78"/>
   </Row>
   <!--beginDetail-->
   <!--where:ma_tc='3' and sysorder =5--where-->
   <Row>
    <Cell ss:Index="2" ss:StyleID="s73"><Data ss:Type="String">#stt#</Data></Cell>
    <Cell ss:StyleID="s73"><Data ss:Type="String">#so_seri#</Data></Cell>
    <Cell ss:StyleID="s73"><Data ss:Type="String">#so_hd#</Data></Cell>
    <Cell ss:StyleID="s90">#ngay_hd#</Cell>
    <Cell ss:StyleID="s73"><Data ss:Type="String">#ten_kh#</Data></Cell>
    <Cell ss:StyleID="s74"><Data ss:Type="String">#ma_so_thue#</Data></Cell>
    <Cell ss:StyleID="s73"><Data ss:Type="String">#ten_vt#</Data></Cell>
    <Cell ss:StyleID="s75"><Data ss:Type="Number">#t_tien#</Data></Cell>
    <Cell ss:StyleID="s73"><Data ss:Type="String">#thue_suat#</Data></Cell>
    <Cell ss:StyleID="s75"><Data ss:Type="Number">#t_thue#</Data></Cell>
    <Cell ss:StyleID="s73"><Data ss:Type="String">#ghi_chu#</Data></Cell>
   </Row>
   <!--endDetail-->
   <!--beginDetail-->
   <!--where:ma_tc='3' and sysorder =3--where-->
   <Row ss:StyleID="s89">
    <Cell ss:Index="2" ss:StyleID="s86"><Data ss:Type="String">Tổng</Data></Cell>
    <Cell ss:StyleID="s87"/>
    <Cell ss:StyleID="s86"/>
    <Cell ss:StyleID="s87"/>
    <Cell ss:StyleID="s87"/>
    <Cell ss:StyleID="s87"/>
    <Cell ss:StyleID="s87"/>
    <Cell ss:StyleID="s88"><Data ss:Type="Number">#t_tien#</Data></Cell>
    <Cell ss:StyleID="s87"/>
    <Cell ss:StyleID="s88"><Data ss:Type="Number">#t_thue#</Data></Cell>
    <Cell ss:StyleID="s87"/>
   </Row>
   <!--endDetail-->
   <Row ss:StyleID="s89">
    <Cell ss:Index="2" ss:MergeAcross="6" ss:StyleID="s114"><Data ss:Type="String">4. Hàng hóa, dịch vụ dùng cho dự án đầu tư đủ điều kiện được khấu trừ thuế:</Data></Cell>
    <Cell ss:StyleID="s79"/>
    <Cell ss:StyleID="s80"/>
    <Cell ss:StyleID="s79"/>
    <Cell ss:StyleID="s78"/>
   </Row>
   <!--beginDetail-->
   <!--where:ma_tc='4' and sysorder =5--where-->
   <Row>
    <Cell ss:Index="2" ss:StyleID="s73"><Data ss:Type="String">#stt#</Data></Cell>
    <Cell ss:StyleID="s73"><Data ss:Type="String">#so_seri#</Data></Cell>
    <Cell ss:StyleID="s73"><Data ss:Type="String">#so_hd#</Data></Cell>
    <Cell ss:StyleID="s90">#ngay_hd#</Cell>
    <Cell ss:StyleID="s73"><Data ss:Type="String">#ten_kh#</Data></Cell>
    <Cell ss:StyleID="s74"><Data ss:Type="String">#ma_so_thue#</Data></Cell>
    <Cell ss:StyleID="s73"><Data ss:Type="String">#ten_vt#</Data></Cell>
    <Cell ss:StyleID="s75"><Data ss:Type="Number">#t_tien#</Data></Cell>
    <Cell ss:StyleID="s73"><Data ss:Type="String">#thue_suat#</Data></Cell>
    <Cell ss:StyleID="s75"><Data ss:Type="Number">#t_thue#</Data></Cell>
    <Cell ss:StyleID="s73"><Data ss:Type="String">#ghi_chu#</Data></Cell>
   </Row>
   <!--endDetail-->
   <!--beginDetail-->
   <!--where:ma_tc='4' and sysorder =3--where-->
   <Row ss:StyleID="s89">
    <Cell ss:Index="2" ss:StyleID="s86"><Data ss:Type="String">Tổng</Data></Cell>
    <Cell ss:StyleID="s87"/>
    <Cell ss:StyleID="s86"/>
    <Cell ss:StyleID="s87"/>
    <Cell ss:StyleID="s87"/>
    <Cell ss:StyleID="s87"/>
    <Cell ss:StyleID="s87"/>
    <Cell ss:StyleID="s88"><Data ss:Type="Number">#t_tien#</Data></Cell>
    <Cell ss:StyleID="s87"/>
    <Cell ss:StyleID="s88"><Data ss:Type="Number">#t_thue#</Data></Cell>
    <Cell ss:StyleID="s87"/>
   </Row>
   <!--endDetail-->
   <Row ss:AutoFitHeight="0">
    <Cell ss:Index="2" ss:MergeAcross="6" ss:StyleID="s114"><Data ss:Type="String">5. Hàng hóa, dịch vụ không phải tổng hợp trên tờ khai 01/GTGT:</Data></Cell>
    <Cell ss:StyleID="s79"/>
    <Cell ss:StyleID="s80"/>
    <Cell ss:StyleID="s79"/>
    <Cell ss:StyleID="s78"/>
   </Row>
   <!--beginDetail-->
   <!--where:ma_tc='5' and sysorder =5--where-->
   <Row>
    <Cell ss:Index="2" ss:StyleID="s73"><Data ss:Type="String">#stt#</Data></Cell>
    <Cell ss:StyleID="s73"><Data ss:Type="String">#so_seri#</Data></Cell>
    <Cell ss:StyleID="s73"><Data ss:Type="String">#so_hd#</Data></Cell>
    <Cell ss:StyleID="s90">#ngay_hd#</Cell>
    <Cell ss:StyleID="s73"><Data ss:Type="String">#ten_kh#</Data></Cell>
    <Cell ss:StyleID="s74"><Data ss:Type="String">#ma_so_thue#</Data></Cell>
    <Cell ss:StyleID="s73"><Data ss:Type="String">#ten_vt#</Data></Cell>
    <Cell ss:StyleID="s75"><Data ss:Type="Number">#t_tien#</Data></Cell>
    <Cell ss:StyleID="s73"><Data ss:Type="String">#thue_suat#</Data></Cell>
    <Cell ss:StyleID="s75"><Data ss:Type="Number">#t_thue#</Data></Cell>
    <Cell ss:StyleID="s73"><Data ss:Type="String">#ghi_chu#</Data></Cell>
   </Row>
   <!--endDetail-->
   <!--beginDetail-->
   <!--where:ma_tc='5' and sysorder =3--where-->
   <Row ss:StyleID="s89">
    <Cell ss:Index="2" ss:StyleID="s86"><Data ss:Type="String">Tổng</Data></Cell>
    <Cell ss:StyleID="s87"/>
    <Cell ss:StyleID="s86"/>
    <Cell ss:StyleID="s87"/>
    <Cell ss:StyleID="s87"/>
    <Cell ss:StyleID="s87"/>
    <Cell ss:StyleID="s87"/>
    <Cell ss:StyleID="s88"><Data ss:Type="Number">#t_tien#</Data></Cell>
    <Cell ss:StyleID="s87"/>
    <Cell ss:StyleID="s88"><Data ss:Type="Number">#t_thue#</Data></Cell>
    <Cell ss:StyleID="s87"/>
   </Row>
   <!--endDetail-->
   <Row>
    <Cell ss:Index="2" ss:StyleID="s66"/>
   </Row>
   <!--beginDetail-->
   <!--where:sysorder=0--where-->
   <Row>
    <Cell ss:Index="2"><Data ss:Type="String">Tổng giá trị hàng hoá, dịch vụ mua vào:             #t_tien#</Data></Cell>
   </Row>
   <Row>
    <Cell ss:Index="2"><Data ss:Type="String">Tổng thuế GTGT của hàng hoá, dịch vụ mua vào:    #t_thue#</Data></Cell>
   </Row>
   <!--endDetail-->
   <Row>
    <Cell ss:Index="2" ss:StyleID="s67"/>
   </Row>
   <Row>
    <Cell ss:Index="2" ss:StyleID="s67"/>
    <Cell ss:Index="9" ss:MergeAcross="3" ss:StyleID="s64"><Data ss:Type="String">..............., ngày......... tháng........... năm..........</Data></Cell>
   </Row>
   <Row>
    <Cell ss:Index="9" ss:MergeAcross="3" ss:StyleID="s64"><Data ss:Type="String">NGƯỜI NỘP THUẾ hoặc</Data></Cell>
   </Row>
   <Row>
    <Cell ss:Index="9" ss:MergeAcross="3" ss:StyleID="s64"><Data ss:Type="String">ĐẠI DIỆN HỢP PHÁP CỦA NGƯỜI NỘP THUẾ</Data></Cell>
   </Row>
   <Row>
    <Cell ss:Index="9" ss:MergeAcross="3" ss:StyleID="s64"><Data ss:Type="String"> Ký tên, đóng dấu (ghi rõ họ tên và chức vụ)</Data></Cell>
   </Row>
  </Table>
  <WorksheetOptions xmlns="urn:schemas-microsoft-com:office:excel">
   <Print>
    <ValidPrinterInfo/>
    <HorizontalResolution>200</HorizontalResolution>
    <VerticalResolution>200</VerticalResolution>
   </Print>
   <Selected/>
   <Panes>
    <Pane>
     <Number>3</Number>
     <ActiveRow>39</ActiveRow>
     <ActiveCol>4</ActiveCol>
    </Pane>
   </Panes>
   <ProtectObjects>False</ProtectObjects>
   <ProtectScenarios>False</ProtectScenarios>
  </WorksheetOptions>
 </Worksheet>
 <Worksheet ss:Name="Huong dan">
  <Table ss:ExpandedColumnCount="16" ss:ExpandedRowCount="35" x:FullColumns="1"
   x:FullRows="1">
   <Column ss:AutoFitWidth="0" ss:Width="17.25"/>
   <Column ss:AutoFitWidth="0" ss:Width="32.25"/>
   <Column ss:AutoFitWidth="0" ss:Width="40.5"/>
   <Column ss:Index="16" ss:AutoFitWidth="0" ss:Width="55.5"/>
   <Row ss:Height="13.5"/>
   <Row ss:AutoFitHeight="0" ss:Height="15.75">
    <Cell ss:Index="2" ss:MergeAcross="14" ss:StyleID="m35104064"><Data
      ss:Type="String">HƯỚNG DẪN LÀM FILE DỮ LIỆU TEMPLATE CHUẨN</Data></Cell>
   </Row>
   <Row ss:AutoFitHeight="0" ss:Height="15.75">
    <Cell ss:Index="2" ss:MergeAcross="14" ss:StyleID="m35104084"><Data
      ss:Type="String">I. Các chú ý khi tạo File Template</Data></Cell>
   </Row>
   <Row>
    <Cell ss:Index="2" ss:StyleID="s81"/>
    <Cell ss:MergeAcross="13" ss:StyleID="m35104124"><Data ss:Type="String">1. Không được thay đổi thứ tự các cột trong file Template</Data></Cell>
   </Row>
   <Row>
    <Cell ss:Index="2" ss:StyleID="s81"/>
    <Cell ss:MergeAcross="13" ss:StyleID="m35104144"><Data ss:Type="String">2. Các mục trong file Template phải đủ 5 mục, mục nào không có dữ liệu phải để một dòng trắng liền sau đó. Các mục bao gồm</Data></Cell>
   </Row>
   <Row>
    <Cell ss:Index="2" ss:StyleID="s81"/>
    <Cell ss:StyleID="s82"/>
    <Cell ss:MergeAcross="12" ss:StyleID="m35104204"><Data ss:Type="String"
      x:Ticked="1">1. Hàng hoá, dịch vụ dùng riêng cho SXKD chịu thuế GTGT đủ điều kiện khấu trừ thuế:</Data></Cell>
   </Row>
   <Row>
    <Cell ss:Index="2" ss:StyleID="s81"/>
    <Cell ss:StyleID="s82"/>
    <Cell ss:MergeAcross="12" ss:StyleID="m35104224"><Data ss:Type="String">2. Hàng hoá, dịch vụ không đủ điều kiện khấu trừ:</Data></Cell>
   </Row>
   <Row>
    <Cell ss:Index="2" ss:StyleID="s81"/>
    <Cell ss:StyleID="s82"/>
    <Cell ss:MergeAcross="12" ss:StyleID="m35104244"><Data ss:Type="String">3. Hàng hoá, dịch vụ dùng chung cho SXKD chịu thuế và không chịu thuế đủ điều kiện khấu trừ thuế:</Data></Cell>
   </Row>
   <Row>
    <Cell ss:Index="2" ss:StyleID="s81"/>
    <Cell ss:StyleID="s82"/>
    <Cell ss:MergeAcross="12" ss:StyleID="m35104552"><Data ss:Type="String">4. Hàng hóa, dịch vụ dùng cho dự án đầu tư đủ điều kiện được khấu trừ thuế:</Data></Cell>
   </Row>
   <Row>
    <Cell ss:Index="2" ss:StyleID="s81"/>
    <Cell ss:StyleID="s82"/>
    <Cell ss:MergeAcross="12" ss:StyleID="m35104632"><Data ss:Type="String">5. Hàng hóa, dịch vụ không phải tổng hợp trên tờ khai 01/GTGT:</Data></Cell>
   </Row>
   <Row>
    <Cell ss:Index="2" ss:StyleID="s81"/>
    <Cell ss:MergeAcross="13" ss:StyleID="m35104164"><Data ss:Type="String">3. Ứng dụng HTKK sẽ nhận dạng ra dữ liệu của bảng kê tại Cell có vị trí Cột (C), Dòng (18)</Data></Cell>
   </Row>
   <Row>
    <Cell ss:Index="2" ss:StyleID="s81"/>
    <Cell ss:MergeAcross="13" ss:StyleID="m35104184"><Data ss:Type="String">4. Sau khi có dữ liệu đầy đủ trong file Template, người sử dụng thiết lập đúng Font để dữ liệu hiển thị được đúng tiếng việt trước khi thực hiện việc Import.</Data></Cell>
   </Row>
   <Row>
    <Cell ss:Index="2" ss:StyleID="s81"/>
    <Cell ss:StyleID="s82"/>
    <Cell ss:StyleID="s82"/>
    <Cell ss:StyleID="s82"/>
    <Cell ss:StyleID="s82"/>
    <Cell ss:StyleID="s82"/>
    <Cell ss:StyleID="s82"/>
    <Cell ss:StyleID="s82"/>
    <Cell ss:StyleID="s82"/>
    <Cell ss:StyleID="s82"/>
    <Cell ss:StyleID="s82"/>
    <Cell ss:StyleID="s82"/>
    <Cell ss:StyleID="s82"/>
    <Cell ss:StyleID="s82"/>
    <Cell ss:StyleID="s83"/>
   </Row>
   <Row>
    <Cell ss:Index="2" ss:MergeAcross="14" ss:StyleID="m35104104"><Data
      ss:Type="String">II. Các kiểm tra để biết dữ liệu file Template là đúng.</Data></Cell>
   </Row>
   <Row>
    <Cell ss:Index="2" ss:StyleID="s81"/>
    <Cell ss:MergeAcross="13" ss:StyleID="m35104612"><Data ss:Type="String">1. Thứ tự các cột đúng như sau</Data></Cell>
   </Row>
   <Row>
    <Cell ss:Index="2" ss:StyleID="s81"/>
    <Cell ss:StyleID="s91"/>
    <Cell ss:MergeAcross="12" ss:StyleID="m35104652"><Data ss:Type="String"
      x:Ticked="1">- Cột STT [1] - Dữ liệu bắt buộc nhập</Data></Cell>
   </Row>
   <Row>
    <Cell ss:Index="2" ss:StyleID="s81"/>
    <Cell ss:StyleID="s82"/>
    <Cell ss:MergeAcross="12" ss:StyleID="m35104572"><Data ss:Type="String"
      x:Ticked="1">- Ký hiệu hóa đơn [2] - Tương ứng với Cột (C) trên file Excel</Data></Cell>
   </Row>
   <Row>
    <Cell ss:Index="2" ss:StyleID="s81"/>
    <Cell ss:StyleID="s82"/>
    <Cell ss:MergeAcross="12" ss:StyleID="m35104592"><Data ss:Type="String"
      x:Ticked="1">- Số hóa đơn [3] - Tương ứng với cột (D) trên file Excel</Data></Cell>
   </Row>
   <Row>
    <Cell ss:Index="2" ss:StyleID="s81"/>
    <Cell ss:StyleID="s82"/>
    <Cell ss:MergeAcross="12" ss:StyleID="m35104672"><Data ss:Type="String"
      x:Ticked="1">- Ngày tháng năm phát hành [4] - Tương ứng với cột (E) trên file Excel</Data></Cell>
   </Row>
   <Row>
    <Cell ss:Index="2" ss:StyleID="s81"/>
    <Cell ss:StyleID="s82"/>
    <Cell ss:MergeAcross="12" ss:StyleID="m35104692"><Data ss:Type="String"
      x:Ticked="1">- Tên người bán [5] - Tương ứng với cột (F) trên file Excel</Data></Cell>
   </Row>
   <Row>
    <Cell ss:Index="2" ss:StyleID="s81"/>
    <Cell ss:StyleID="s82"/>
    <Cell ss:MergeAcross="12" ss:StyleID="m35104736"><Data ss:Type="String"
      x:Ticked="1">- Mã số thuế người bán [6] - Tương ứng với cột (G) trên file Excel</Data></Cell>
   </Row>
   <Row>
    <Cell ss:Index="2" ss:StyleID="s81"/>
    <Cell ss:StyleID="s82"/>
    <Cell ss:MergeAcross="12" ss:StyleID="m35104756"><Data ss:Type="String"
      x:Ticked="1">- Mặt hàng [7] - Tương ứng với cột (H) trên file Excel</Data></Cell>
   </Row>
   <Row>
    <Cell ss:Index="2" ss:StyleID="s81"/>
    <Cell ss:StyleID="s82"/>
    <Cell ss:MergeAcross="12" ss:StyleID="m35104512"><Data ss:Type="String"
      x:Ticked="1">- Doanh số mua chưa có thuế [8] - Tương ứng với cột (I) trên file Excel</Data></Cell>
   </Row>
   <Row>
    <Cell ss:Index="2" ss:StyleID="s81"/>
    <Cell ss:StyleID="s82"/>
    <Cell ss:MergeAcross="12" ss:StyleID="m35104532"><Data ss:Type="String"
      x:Ticked="1">- Thuế suất [9] - Tương ứng với cột (J) trên file Excel</Data></Cell>
   </Row>
   <Row>
    <Cell ss:Index="2" ss:StyleID="s81"/>
    <Cell ss:StyleID="s82"/>
    <Cell ss:MergeAcross="12" ss:StyleID="m35104308"><Data ss:Type="String"
      x:Ticked="1">- Thuế GTGT [10] - Tương ứng với cột (K) trên file Excel</Data></Cell>
   </Row>
   <Row>
    <Cell ss:Index="2" ss:StyleID="s81"/>
    <Cell ss:StyleID="s82"/>
    <Cell ss:MergeAcross="12" ss:StyleID="m35104328"><Data ss:Type="String"
      x:Ticked="1">- Ghi chú [11] - Tương ứng với cột (L) trên file Excel</Data></Cell>
   </Row>
   <Row>
    <Cell ss:Index="2" ss:StyleID="s81"/>
    <Cell ss:StyleID="s82"/>
    <Cell ss:StyleID="s82"/>
    <Cell ss:StyleID="s82"/>
    <Cell ss:StyleID="s82"/>
    <Cell ss:StyleID="s82"/>
    <Cell ss:StyleID="s82"/>
    <Cell ss:StyleID="s82"/>
    <Cell ss:StyleID="s82"/>
    <Cell ss:StyleID="s82"/>
    <Cell ss:StyleID="s82"/>
    <Cell ss:StyleID="s82"/>
    <Cell ss:StyleID="s82"/>
    <Cell ss:StyleID="s82"/>
    <Cell ss:StyleID="s83"/>
   </Row>
   <Row>
    <Cell ss:Index="2" ss:StyleID="s81"/>
    <Cell ss:MergeAcross="13" ss:StyleID="m35104388"><Data ss:Type="String">2. Định dạng chuẩn cho các cột</Data></Cell>
   </Row>
   <Row>
    <Cell ss:Index="2" ss:StyleID="s81"/>
    <Cell ss:StyleID="s82"/>
    <Cell ss:MergeAcross="12" ss:StyleID="m35104348"><Data ss:Type="String"
      x:Ticked="1">- Các cột C, D,F, G, H, L: phải là kiểuText</Data></Cell>
   </Row>
   <Row>
    <Cell ss:Index="2" ss:StyleID="s81"/>
    <Cell ss:StyleID="s82"/>
    <Cell ss:MergeAcross="12" ss:StyleID="m35104408"><Data ss:Type="String"
      x:Ticked="1">- Cột C (Ký hiệu hóa đơn), D (Số hóa đơn) chỉ được nhập tối đa là 20 ký tự</Data></Cell>
   </Row>
   <Row>
    <Cell ss:Index="2" ss:StyleID="s81"/>
    <Cell ss:StyleID="s82"/>
    <Cell ss:MergeAcross="12" ss:StyleID="m35104468"><Data ss:Type="String"
      x:Ticked="1">- Cột E (Ngày tháng năm phát hành) là định dang theo kiêu Date: DD/MM/YYYY</Data></Cell>
   </Row>
   <Row>
    <Cell ss:Index="2" ss:StyleID="s81"/>
    <Cell ss:StyleID="s82"/>
    <Cell ss:MergeAcross="12" ss:StyleID="m35104428"><Data ss:Type="String"
      x:Ticked="1">- Cột F (Tên người mua), H (Mặt hàng) chỉ được nhập tối đa 100 ký tự</Data></Cell>
   </Row>
   <Row ss:AutoFitHeight="0" ss:Height="25.5">
    <Cell ss:Index="2" ss:StyleID="s81"/>
    <Cell ss:StyleID="s82"/>
    <Cell ss:MergeAcross="12" ss:StyleID="m35104448"><Data ss:Type="String"
      x:Ticked="1">- Cột G (Mã số thuế) chỉ được nhập tối đa 14 ký tự. 10 ký tự đầu là MST, 3 ký tự cuối cùng số thứ tự của chi nhánh (Nếu có), ký tự 11 là dấu - hoặc dấu trắng để ngăn cách</Data></Cell>
   </Row>
   <Row>
    <Cell ss:Index="2" ss:StyleID="s81"/>
    <Cell ss:StyleID="s82"/>
    <Cell ss:MergeAcross="12" ss:StyleID="m35104368"><Data ss:Type="String"
      x:Ticked="1">- Các cột I (Doanh số mua chưa có thuế), K (Thuế GTGT) phải là kiểu Số</Data></Cell>
   </Row>
   <Row ss:Height="13.5">
    <Cell ss:Index="2" ss:StyleID="s84"/>
    <Cell ss:StyleID="s85"/>
    <Cell ss:MergeAcross="12" ss:StyleID="m35104288"><Data ss:Type="String"
      x:Ticked="1">- Dữ liệu cột J (Thuế suất) định dạng theo kiểu Text</Data></Cell>
   </Row>
  </Table>
  <WorksheetOptions xmlns="urn:schemas-microsoft-com:office:excel">
   <Panes>
    <Pane>
     <Number>3</Number>
     <ActiveRow>10</ActiveRow>
     <ActiveCol>2</ActiveCol>
     <RangeSelection>R11C3:R11C16</RangeSelection>
    </Pane>
   </Panes>
   <ProtectObjects>False</ProtectObjects>
   <ProtectScenarios>False</ProtectScenarios>
  </WorksheetOptions>
 </Worksheet>
</Workbook>
