<?xml version="1.0" standalone="yes"?>
<NewDataSet>
  <xs:schema id="NewDataSet" xmlns="" xmlns:xs="http://www.w3.org/2001/XMLSchema" xmlns:msdata="urn:schemas-microsoft-com:xml-msdata">
    <xs:element name="NewDataSet" msdata:IsDataSet="true" msdata:MainDataTable="rtkgtgt" msdata:UseCurrentLocale="true">
      <xs:complexType>
        <xs:choice minOccurs="0" maxOccurs="unbounded">
          <xs:element name="rtkgtgt">
            <xs:complexType>
              <xs:sequence>
                <xs:element name="FormID" type="xs:string" minOccurs="0" />
                <xs:element name="TextID" type="xs:string" minOccurs="0" />
                <xs:element name="TextV" type="xs:string" minOccurs="0" />
                <xs:element name="TextE" type="xs:string" minOccurs="0" />
              </xs:sequence>
            </xs:complexType>
          </xs:element>
        </xs:choice>
      </xs:complexType>
    </xs:element>
  </xs:schema>
  <rtkgtgt>
    <FormID>rtkgtgt</FormID>
    <TextID>000</TextID>
    <TextV>Tờ khai thuế giá trị gia tăng</TextV>
    <TextE>VAT Declaration</TextE>
  </rtkgtgt>
  <rtkgtgt>
    <FormID>rtkgtgt</FormID>
    <TextID>001</TextID>
    <TextV>Điều kiện lọc</TextV>
    <TextE>Filter Condition</TextE>
  </rtkgtgt>
  <rtkgtgt>
    <FormID>rtkgtgt</FormID>
    <TextID>002</TextID>
    <TextV>Từ tháng/đến tháng</TextV>
    <TextE>Month from/to</TextE>
  </rtkgtgt>
  <rtkgtgt>
    <FormID>rtkgtgt</FormID>
    <TextID>003</TextID>
    <TextV>Kỳ trước</TextV>
    <TextE>Previous Period</TextE>
  </rtkgtgt>
  <rtkgtgt>
    <FormID>rtkgtgt</FormID>
    <TextID>004</TextID>
    <TextV>Ngày cuối kỳ trước</TextV>
    <TextE>Ending Date Prev. Period</TextE>
  </rtkgtgt>
  <rtkgtgt>
    <FormID>rtkgtgt</FormID>
    <TextID>005</TextID>
    <TextV>Nhóm vật tư</TextV>
    <TextE>Item Group</TextE>
  </rtkgtgt>
  <rtkgtgt>
    <FormID>rtkgtgt</FormID>
    <TextID>006</TextID>
    <TextV>Loại vật tư</TextV>
    <TextE>Item Type</TextE>
  </rtkgtgt>
  <rtkgtgt>
    <FormID>rtkgtgt</FormID>
    <TextID>007</TextID>
    <TextV>In cả chứng từ điều chuyển</TextV>
    <TextE>Print the document transfer</TextE>
  </rtkgtgt>
  <rtkgtgt>
    <FormID>rtkgtgt</FormID>
    <TextID>008</TextID>
    <TextV>Không in vật tư tồn =0</TextV>
    <TextE>No Print Item Exist =0</TextE>
  </rtkgtgt>
  <rtkgtgt>
    <FormID>rtkgtgt</FormID>
    <TextID>009</TextID>
    <TextV>Đơn vị</TextV>
    <TextE>Unit</TextE>
  </rtkgtgt>
  <rtkgtgt>
    <FormID>rtkgtgt</FormID>
    <TextID>010</TextID>
    <TextV>Nhóm theo</TextV>
    <TextE>Group by</TextE>
  </rtkgtgt>
  <rtkgtgt>
    <FormID>rtkgtgt</FormID>
    <TextID>011</TextID>
    <TextV>Mẫu báo cáo</TextV>
    <TextE>Report Form</TextE>
  </rtkgtgt>
  <rtkgtgt>
    <FormID>rtkgtgt</FormID>
    <TextID>012</TextID>
    <TextV>Tiêu đề</TextV>
    <TextE>Title</TextE>
  </rtkgtgt>
  <rtkgtgt>
    <FormID>rtkgtgt</FormID>
    <TextID>013</TextID>
    <TextV>HTKKT</TextV>
    <TextE>HTKKT</TextE>
  </rtkgtgt>
  <rtkgtgt>
    <FormID>rtkgtgt</FormID>
    <TextID>020</TextID>
    <TextV>Sửa mẫu</TextV>
    <TextE>Edit Form</TextE>
  </rtkgtgt>
  <rtkgtgt>
    <FormID>rtkgtgt</FormID>
    <TextID>022</TextID>
    <TextV>Khai báo mẫu</TextV>
    <TextE>Declaration Form</TextE>
  </rtkgtgt>
  <rtkgtgt>
    <FormID>rtkgtgt</FormID>
    <TextID>023</TextID>
    <TextV>STT</TextV>
    <TextE>No.</TextE>
  </rtkgtgt>
  <rtkgtgt>
    <FormID>rtkgtgt</FormID>
    <TextID>024</TextID>
    <TextV>Mã số</TextV>
    <TextE>Code</TextE>
  </rtkgtgt>
  <rtkgtgt>
    <FormID>rtkgtgt</FormID>
    <TextID>025</TextID>
    <TextV>Chỉ tiêu</TextV>
    <TextE>Article</TextE>
  </rtkgtgt>
  <rtkgtgt>
    <FormID>rtkgtgt</FormID>
    <TextID>026</TextID>
    <TextV>Chỉ tiêu 2</TextV>
    <TextE>Article 2</TextE>
  </rtkgtgt>
  <rtkgtgt>
    <FormID>rtkgtgt</FormID>
    <TextID>027</TextID>
    <TextV>Thuyết minh</TextV>
    <TextE>Interpretation</TextE>
  </rtkgtgt>
  <rtkgtgt>
    <FormID>rtkgtgt</FormID>
    <TextID>028</TextID>
    <TextV>Phân loại</TextV>
    <TextE>Classify</TextE>
  </rtkgtgt>
  <rtkgtgt>
    <FormID>rtkgtgt</FormID>
    <TextID>029</TextID>
    <TextV>Chỉ tiêu ngoài bảng</TextV>
    <TextE>Article outside the table</TextE>
  </rtkgtgt>
  <rtkgtgt>
    <FormID>rtkgtgt</FormID>
    <TextID>030</TextID>
    <TextV>In</TextV>
    <TextE>Print</TextE>
  </rtkgtgt>
  <rtkgtgt>
    <FormID>rtkgtgt</FormID>
    <TextID>031</TextID>
    <TextV>In đậm</TextV>
    <TextE>Bold</TextE>
  </rtkgtgt>
  <rtkgtgt>
    <FormID>rtkgtgt</FormID>
    <TextID>032</TextID>
    <TextV>Phương pháp tính</TextV>
    <TextE>Method</TextE>
  </rtkgtgt>
  <rtkgtgt>
    <FormID>rtkgtgt</FormID>
    <TextID>033</TextID>
    <TextV>Tài khoản nợ</TextV>
    <TextE>Dr. Account</TextE>
  </rtkgtgt>
  <rtkgtgt>
    <FormID>rtkgtgt</FormID>
    <TextID>034</TextID>
    <TextV>Tính giảm trừ</TextV>
    <TextE>Calculate Way</TextE>
  </rtkgtgt>
  <rtkgtgt>
    <FormID>rtkgtgt</FormID>
    <TextID>035</TextID>
    <TextV>Tài khoản có</TextV>
    <TextE>Cr. Account</TextE>
  </rtkgtgt>
  <rtkgtgt>
    <FormID>rtkgtgt</FormID>
    <TextID>036</TextID>
    <TextV>Công thức</TextV>
    <TextE>Formula</TextE>
  </rtkgtgt>
  <rtkgtgt>
    <FormID>rtkgtgt</FormID>
    <TextID>037</TextID>
    <TextV>&amp;Lưu</TextV>
    <TextE>&amp;Save</TextE>
  </rtkgtgt>
  <rtkgtgt>
    <FormID>rtkgtgt</FormID>
    <TextID>038</TextID>
    <TextV>&amp;Hủy</TextV>
    <TextE>&amp;Cancel</TextE>
  </rtkgtgt>
  <rtkgtgt>
    <FormID>rtkgtgt</FormID>
    <TextID>039</TextID>
    <TextV>Chỉ tiêu này không được xóa</TextV>
    <TextE>This criterion is not clear</TextE>
  </rtkgtgt>
  <rtkgtgt>
    <FormID>rtkgtgt</FormID>
    <TextID>040</TextID>
    <TextV>STT in</TextV>
    <TextE>No. Print</TextE>
  </rtkgtgt>
  <rtkgtgt>
    <FormID>rtkgtgt</FormID>
    <TextID>041</TextID>
    <TextV>Mã in[Tiền]</TextV>
    <TextE>Code [Amount]</TextE>
  </rtkgtgt>
  <rtkgtgt>
    <FormID>rtkgtgt</FormID>
    <TextID>042</TextID>
    <TextV>Mã in[Thuế]</TextV>
    <TextE>Code [Tax]</TextE>
  </rtkgtgt>
  <rtkgtgt>
    <FormID>rtkgtgt</FormID>
    <TextID>043</TextID>
    <TextV>Kiểu hiện</TextV>
    <TextE>Type Show</TextE>
  </rtkgtgt>
  <rtkgtgt>
    <FormID>rtkgtgt</FormID>
    <TextID>044</TextID>
    <TextV>Lấy từ bảng</TextV>
    <TextE>Take from table</TextE>
  </rtkgtgt>
  <rtkgtgt>
    <FormID>rtkgtgt</FormID>
    <TextID>045</TextID>
    <TextV>Mã thuế</TextV>
    <TextE>Tax Code</TextE>
  </rtkgtgt>
  <rtkgtgt>
    <FormID>rtkgtgt</FormID>
    <TextID>046</TextID>
    <TextV>Chỉ tính chứng từ có thuế (đầu vào)</TextV>
    <TextE>Voucher with Tax only (input)</TextE>
  </rtkgtgt>
  <rtkgtgt>
    <FormID>rtkgtgt</FormID>
    <TextID>200</TextID>
    <TextV>Chức năng</TextV>
    <TextE>&amp;Function</TextE>
  </rtkgtgt>
  <rtkgtgt>
    <FormID>rtkgtgt</FormID>
    <TextID>201</TextID>
    <TextV>In</TextV>
    <TextE>Print</TextE>
  </rtkgtgt>
  <rtkgtgt>
    <FormID>rtkgtgt</FormID>
    <TextID>202</TextID>
    <TextV>Xem</TextV>
    <TextE>View</TextE>
  </rtkgtgt>
  <rtkgtgt>
    <FormID>rtkgtgt</FormID>
    <TextID>203</TextID>
    <TextV>Làm tươi</TextV>
    <TextE>Refresh</TextE>
  </rtkgtgt>
  <rtkgtgt>
    <FormID>rtkgtgt</FormID>
    <TextID>204</TextID>
    <TextV>Xem chứng từ</TextV>
    <TextE>View Voucher</TextE>
  </rtkgtgt>
  <rtkgtgt>
    <FormID>rtkgtgt</FormID>
    <TextID>900</TextID>
    <TextV>&amp;Nhận</TextV>
    <TextE>&amp;OK</TextE>
  </rtkgtgt>
  <rtkgtgt>
    <FormID>rtkgtgt</FormID>
    <TextID>901</TextID>
    <TextV>&amp;Hủy</TextV>
    <TextE>&amp;Cancel</TextE>
  </rtkgtgt>
  <rtkgtgt>
    <FormID>rtkgtgt</FormID>
    <TextID>999</TextID>
    <TextV>Thoát</TextV>
    <TextE>&amp;Close</TextE>
  </rtkgtgt>
</NewDataSet>